quoridor_env-0.2.6.dist-info/licenses/LICENSE
quoridor_sim/__init__.py
quoridor_sim/board.py
quoridor_sim/core.py
quoridor_sim/episode_logger.py
quoridor_sim/players.py
quoridor_sim/quoridor_env.py
quoridor_sim/renderer.py
quoridor_env-0.2.6.dist-info/METADATA
quoridor_env-0.2.6.dist-info/WHEEL
quoridor_env-0.2.6.dist-info/top_level.txt
quoridor_env-0.2.6.dist-info/RECORD
