Metadata-Version: 2.4
Name: quoridor-env
Version: 0.2.6
Summary: Python Quoridor game engine with Gym environment for RL
Home-page: https://github.com/chrisjcc/quoridor
Author: Christian Contreras
Author-email: chrisjcc@users.noreply.github.com
License: MIT
Keywords: quoridor gymnasium reinforcement-learning board-game
Classifier: Programming Language :: Python :: 3
Classifier: Operating System :: OS Independent
Classifier: Intended Audience :: Developers
Classifier: Topic :: Games/Entertainment :: Board Games
Classifier: Topic :: Software Development :: Libraries
Requires-Python: >=3.8
License-File: LICENSE
Requires-Dist: gymnasium>=0.28.0
Requires-Dist: numpy>=1.23
Requires-Dist: fastapi>=0.104.0
Requires-Dist: pydantic>=2.0.0
Requires-Dist: uvicorn[standard]>=0.24.0
Dynamic: author
Dynamic: author-email
Dynamic: classifier
Dynamic: description
Dynamic: description-content-type
Dynamic: home-page
Dynamic: keywords
Dynamic: license
Dynamic: license-file
Dynamic: requires-dist
Dynamic: requires-python
Dynamic: summary
